{
  "book_id": "beatles-complete-scores-2",
  "toc": {
    "entries": [],
    "extraction_method": "bedrock_vision",
    "confidence": 0.0,
    "artist_overrides": {}
  },
  "output": {
    "output_files": [
      {
        "song_title": "Across the Universe",
        "artist": "Beatles",
        "output_uri": "s3://jsmith-output/Beatles/Complete Scores (2)/Songs/John Lennon & Paul Mccartney - Across The Universe.pdf",
        "file_size_bytes": 397328,
        "page_range": [
          2,
          8
        ]
      },
      {
        "song_title": "Act Naturally",
        "artist": "Beatles",
        "output_uri": "s3://jsmith-output/Beatles/Complete Scores (2)/Songs/Words By Vance Morrison, Music By Johnny Russell - Act Naturally.pdf",
        "file_size_bytes": 376308,
        "page_range": [
          8,
          14
        ]
      },
      {
        "song_title": "All I've Got to Do",
        "artist": "Beatles",
        "output_uri": "s3://jsmith-output/Beatles/Complete Scores (2)/Songs/John Lennon & Paul Mccartney - All I've Got To Do.pdf",
        "file_size_bytes": 254403,
        "page_range": [
          14,
          18
        ]
      },
      {
        "song_title": "All My Loving",
        "artist": "Beatles",
        "output_uri": "s3://jsmith-output/Beatles/Complete Scores (2)/Songs/John Lennon & Paul Mccartney - All My Loving.pdf",
        "file_size_bytes": 330165,
        "page_range": [
          18,
          23
        ]
      },
      {
        "song_title": "All Together Now",
        "artist": "Beatles",
        "output_uri": "s3://jsmith-output/Beatles/Complete Scores (2)/Songs/John Lennon & Paul Mccartney - All Together Now.pdf",
        "file_size_bytes": 367462,
        "page_range": [
          23,
          29
        ]
      },
      {
        "song_title": "All You Need Is Love",
        "artist": "Beatles",
        "output_uri": "s3://jsmith-output/Beatles/Complete Scores (2)/Songs/John Lennon & Paul Mccartney - All You Need Is Love.pdf",
        "file_size_bytes": 315480,
        "page_range": [
          29,
          34
        ]
      },
      {
        "song_title": "And I Love Her",
        "artist": "Beatles",
        "output_uri": "s3://jsmith-output/Beatles/Complete Scores (2)/Songs/John Lennon & Paul Mccartney - And I Love Her.pdf",
        "file_size_bytes": 296682,
        "page_range": [
          34,
          39
        ]
      },
      {
        "song_title": "And Your Bird Can Sing",
        "artist": "Beatles",
        "output_uri": "s3://jsmith-output/Beatles/Complete Scores (2)/Songs/John Lennon & Paul Mccartney - And Your Bird Can Sing.pdf",
        "file_size_bytes": 392702,
        "page_range": [
          39,
          45
        ]
      },
      {
        "song_title": "Anna (Go To Him)",
        "artist": "Beatles",
        "output_uri": "s3://jsmith-output/Beatles/Complete Scores (2)/Songs/Arthur Alexander - Anna (go To Him).pdf",
        "file_size_bytes": 375625,
        "page_range": [
          45,
          51
        ]
      },
      {
        "song_title": "Another Girl",
        "artist": "Beatles",
        "output_uri": "s3://jsmith-output/Beatles/Complete Scores (2)/Songs/John Lennon & Paul Mccartney - Another Girl.pdf",
        "file_size_bytes": 264286,
        "page_range": [
          51,
          55
        ]
      },
      {
        "song_title": "Any Time At All",
        "artist": "Beatles",
        "output_uri": "s3://jsmith-output/Beatles/Complete Scores (2)/Songs/John Lennon & Paul Mccartney - Any Time At All.pdf",
        "file_size_bytes": 298963,
        "page_range": [
          55,
          60
        ]
      },
      {
        "song_title": "Ask Me Why",
        "artist": "Beatles",
        "output_uri": "s3://jsmith-output/Beatles/Complete Scores (2)/Songs/John Lennon & Paul Mccartney - Ask Me Why.pdf",
        "file_size_bytes": 309641,
        "page_range": [
          60,
          65
        ]
      },
      {
        "song_title": "Baby It's You",
        "artist": "Beatles",
        "output_uri": "s3://jsmith-output/Beatles/Complete Scores (2)/Songs/Hal David, Burt Bacharach & Barney Williams - Baby It's You.pdf",
        "file_size_bytes": 249459,
        "page_range": [
          65,
          69
        ]
      },
      {
        "song_title": "Baby's in Black",
        "artist": "Beatles",
        "output_uri": "s3://jsmith-output/Beatles/Complete Scores (2)/Songs/John Lennon & Paul Mccartney - Baby's In Black.pdf",
        "file_size_bytes": 249013,
        "page_range": [
          69,
          73
        ]
      },
      {
        "song_title": "Baby You're a Rich Man",
        "artist": "Beatles",
        "output_uri": "s3://jsmith-output/Beatles/Complete Scores (2)/Songs/John Lennon & Paul Mccartney - Baby You're A Rich Man.pdf",
        "file_size_bytes": 389047,
        "page_range": [
          73,
          79
        ]
      },
      {
        "song_title": "Back in the USSR",
        "artist": "Beatles",
        "output_uri": "s3://jsmith-output/Beatles/Complete Scores (2)/Songs/John Lennon & Paul Mccartney - Back In The Ussr.pdf",
        "file_size_bytes": 537062,
        "page_range": [
          79,
          86
        ]
      },
      {
        "song_title": "Bad Boy",
        "artist": "Beatles",
        "output_uri": "s3://jsmith-output/Beatles/Complete Scores (2)/Songs/Larry Williams - Bad Boy.pdf",
        "file_size_bytes": 321750,
        "page_range": [
          86,
          91
        ]
      },
      {
        "song_title": "The Ballad of John and Yoko",
        "artist": "Beatles",
        "output_uri": "s3://jsmith-output/Beatles/Complete Scores (2)/Songs/John Lennon & Paul Mccartney - The Ballad Of John And Yoko.pdf",
        "file_size_bytes": 330837,
        "page_range": [
          91,
          96
        ]
      },
      {
        "song_title": "Because",
        "artist": "Beatles",
        "output_uri": "s3://jsmith-output/Beatles/Complete Scores (2)/Songs/John Lennon & Paul Mccartney - Because.pdf",
        "file_size_bytes": 259335,
        "page_range": [
          96,
          100
        ]
      },
      {
        "song_title": "Being for the Benefit of Mr. Kite",
        "artist": "Beatles",
        "output_uri": "s3://jsmith-output/Beatles/Complete Scores (2)/Songs/John Lennon & Paul Mccartney - Being For The Benefit Of Mr. Kite.pdf",
        "file_size_bytes": 382920,
        "page_range": [
          100,
          106
        ]
      },
      {
        "song_title": "Birthday",
        "artist": "Beatles",
        "output_uri": "s3://jsmith-output/Beatles/Complete Scores (2)/Songs/John Lennon & Paul Mccartney - Birthday.pdf",
        "file_size_bytes": 424415,
        "page_range": [
          106,
          112
        ]
      },
      {
        "song_title": "Blackbird",
        "artist": "Beatles",
        "output_uri": "s3://jsmith-output/Beatles/Complete Scores (2)/Songs/John Lennon & Paul Mccartney - Blackbird.pdf",
        "file_size_bytes": 247522,
        "page_range": [
          112,
          116
        ]
      },
      {
        "song_title": "Blue Jay Way",
        "artist": "Beatles",
        "output_uri": "s3://jsmith-output/Beatles/Complete Scores (2)/Songs/George Harrison - Blue Jay Way.pdf",
        "file_size_bytes": 314143,
        "page_range": [
          116,
          121
        ]
      },
      {
        "song_title": "Boys",
        "artist": "Beatles",
        "output_uri": "s3://jsmith-output/Beatles/Complete Scores (2)/Songs/Luther Dixon & Wes Farrell - Boys.pdf",
        "file_size_bytes": 399857,
        "page_range": [
          121,
          127
        ]
      },
      {
        "song_title": "Can't Buy Me Love",
        "artist": "Beatles",
        "output_uri": "s3://jsmith-output/Beatles/Complete Scores (2)/Songs/Words & Music By John Lennon & Paul Mccartney - Can't Buy Me Love.pdf",
        "file_size_bytes": 361316,
        "page_range": [
          127,
          133
        ]
      },
      {
        "song_title": "Carry That Weight",
        "artist": "Beatles",
        "output_uri": "s3://jsmith-output/Beatles/Complete Scores (2)/Songs/Words & Music By John Lennon & Paul Mccartney - Carry That Weight.pdf",
        "file_size_bytes": 265377,
        "page_range": [
          133,
          137
        ]
      },
      {
        "song_title": "Chains",
        "artist": "Beatles",
        "output_uri": "s3://jsmith-output/Beatles/Complete Scores (2)/Songs/Gerry Goffin & Carole King - Chains.pdf",
        "file_size_bytes": 245404,
        "page_range": [
          137,
          141
        ]
      },
      {
        "song_title": "Come Together",
        "artist": "Beatles",
        "output_uri": "s3://jsmith-output/Beatles/Complete Scores (2)/Songs/John Lennon & Paul Mccartney - Come Together.pdf",
        "file_size_bytes": 721352,
        "page_range": [
          141,
          152
        ]
      },
      {
        "song_title": "Cry Baby Cry",
        "artist": "Beatles",
        "output_uri": "s3://jsmith-output/Beatles/Complete Scores (2)/Songs/John Lennon & Paul Mccartney - Cry Baby Cry.pdf",
        "file_size_bytes": 281630,
        "page_range": [
          152,
          156
        ]
      },
      {
        "song_title": "A Day in the Life",
        "artist": "Beatles",
        "output_uri": "s3://jsmith-output/Beatles/Complete Scores (2)/Songs/John Lennon & Paul Mccartney - A Day In The Life.pdf",
        "file_size_bytes": 664098,
        "page_range": [
          156,
          166
        ]
      },
      {
        "song_title": "Day Tripper",
        "artist": "Beatles",
        "output_uri": "s3://jsmith-output/Beatles/Complete Scores (2)/Songs/John Lennon & Paul Mccartney - Day Tripper.pdf",
        "file_size_bytes": 430903,
        "page_range": [
          166,
          173
        ]
      },
      {
        "song_title": "Dear Prudence",
        "artist": "Beatles",
        "output_uri": "s3://jsmith-output/Beatles/Complete Scores (2)/Songs/John Lennon & Paul Mccartney - Dear Prudence.pdf",
        "file_size_bytes": 492724,
        "page_range": [
          173,
          180
        ]
      },
      {
        "song_title": "Devil in Her Heart",
        "artist": "Beatles",
        "output_uri": "s3://jsmith-output/Beatles/Complete Scores (2)/Songs/Richard B. Drapkin - Devil In Her Heart.pdf",
        "file_size_bytes": 276379,
        "page_range": [
          180,
          184
        ]
      },
      {
        "song_title": "Dig a Pony",
        "artist": "Beatles",
        "output_uri": "s3://jsmith-output/Beatles/Complete Scores (2)/Songs/John Lennon & Paul Mccartney - Dig A Pony.pdf",
        "file_size_bytes": 398489,
        "page_range": [
          184,
          190
        ]
      },
      {
        "song_title": "Dig It",
        "artist": "Beatles",
        "output_uri": "s3://jsmith-output/Beatles/Complete Scores (2)/Songs/John Lennon, Paul Mccartney, George Harrison & Richard Starkey - Dig It.pdf",
        "file_size_bytes": 231924,
        "page_range": [
          190,
          194
        ]
      },
      {
        "song_title": "Dizzy Miss Lizzy",
        "artist": "Beatles",
        "output_uri": "s3://jsmith-output/Beatles/Complete Scores (2)/Songs/Larry Williams - Dizzy Miss Lizzy.pdf",
        "file_size_bytes": 344017,
        "page_range": [
          194,
          199
        ]
      },
      {
        "song_title": "Doctor Robert",
        "artist": "Beatles",
        "output_uri": "s3://jsmith-output/Beatles/Complete Scores (2)/Songs/Words & Music By John Lennon & Paul Mccartney - Doctor Robert.pdf",
        "file_size_bytes": 328912,
        "page_range": [
          199,
          204
        ]
      },
      {
        "song_title": "Don't Bother Me",
        "artist": "Beatles",
        "output_uri": "s3://jsmith-output/Beatles/Complete Scores (2)/Songs/George Harrison - Don't Bother Me.pdf",
        "file_size_bytes": 374517,
        "page_range": [
          204,
          210
        ]
      },
      {
        "song_title": "Don't Let Me Down",
        "artist": "Beatles",
        "output_uri": "s3://jsmith-output/Beatles/Complete Scores (2)/Songs/John Lennon & Paul Mccartney - Don't Let Me Down.pdf",
        "file_size_bytes": 341977,
        "page_range": [
          210,
          215
        ]
      },
      {
        "song_title": "Don't Pass Me By",
        "artist": "Beatles",
        "output_uri": "s3://jsmith-output/Beatles/Complete Scores (2)/Songs/(words & Music By Ringo Starr Is Listed, Indicating Ringo Starr As The Artist) - Don't Pass Me By.pdf",
        "file_size_bytes": 409249,
        "page_range": [
          215,
          221
        ]
      },
      {
        "song_title": "Do You Want to Know a Secret?",
        "artist": "Beatles",
        "output_uri": "s3://jsmith-output/Beatles/Complete Scores (2)/Songs/John Lennon, Paul Mccartney - Do You Want To Know A Secret-.pdf",
        "file_size_bytes": 189534,
        "page_range": [
          221,
          224
        ]
      },
      {
        "song_title": "Drive My Car",
        "artist": "Beatles",
        "output_uri": "s3://jsmith-output/Beatles/Complete Scores (2)/Songs/John Lennon & Paul Mccartney - Drive My Car.pdf",
        "file_size_bytes": 339290,
        "page_range": [
          224,
          229
        ]
      },
      {
        "song_title": "Eight Days a Week",
        "artist": "Beatles",
        "output_uri": "s3://jsmith-output/Beatles/Complete Scores (2)/Songs/John Lennon, Paul Mccartney - Eight Days A Week.pdf",
        "file_size_bytes": 237913,
        "page_range": [
          229,
          233
        ]
      },
      {
        "song_title": "Eleanor Rigby",
        "artist": "Beatles",
        "output_uri": "s3://jsmith-output/Beatles/Complete Scores (2)/Songs/Words & Music By John Lennon & Paul Mccartney - Eleanor Rigby.pdf",
        "file_size_bytes": 232251,
        "page_range": [
          233,
          237
        ]
      },
      {
        "song_title": "The End",
        "artist": "Beatles",
        "output_uri": "s3://jsmith-output/Beatles/Complete Scores (2)/Songs/John Lennon & Paul Mccartney - The End.pdf",
        "file_size_bytes": 424298,
        "page_range": [
          237,
          244
        ]
      },
      {
        "song_title": "Everybody's Got Something to Hide Except Me and My Monkey",
        "artist": "Beatles",
        "output_uri": "s3://jsmith-output/Beatles/Complete Scores (2)/Songs/John Lennon And Paul Mccartney - Everybody's Got Something To Hide Except Me And My Monkey.pdf",
        "file_size_bytes": 272301,
        "page_range": [
          244,
          248
        ]
      },
      {
        "song_title": "Everybody's Trying to Be My Baby",
        "artist": "Beatles",
        "output_uri": "s3://jsmith-output/Beatles/Complete Scores (2)/Songs/Carl Lee Perkins - Everybody's Trying To Be My Baby.pdf",
        "file_size_bytes": 481978,
        "page_range": [
          248,
          256
        ]
      },
      {
        "song_title": "Every Little Thing",
        "artist": "Beatles",
        "output_uri": "s3://jsmith-output/Beatles/Complete Scores (2)/Songs/John Lennon & Paul Mccartney - Every Little Thing.pdf",
        "file_size_bytes": 251998,
        "page_range": [
          256,
          260
        ]
      },
      {
        "song_title": "Fixing a Hole",
        "artist": "Beatles",
        "output_uri": "s3://jsmith-output/Beatles/Complete Scores (2)/Songs/John Lennon & Paul Mccartney - Fixing A Hole.pdf",
        "file_size_bytes": 427083,
        "page_range": [
          260,
          267
        ]
      },
      {
        "song_title": "Flying",
        "artist": "Beatles",
        "output_uri": "s3://jsmith-output/Beatles/Complete Scores (2)/Songs/By John Lennon, Paul Mccartney, George Harrison And Richard Starkey - Flying.pdf",
        "file_size_bytes": 316223,
        "page_range": [
          267,
          272
        ]
      },
      {
        "song_title": "Fool on the Hill",
        "artist": "Beatles",
        "output_uri": "s3://jsmith-output/Beatles/Complete Scores (2)/Songs/John Lennon & Paul Mccartney - Fool On The Hill.pdf",
        "file_size_bytes": 345940,
        "page_range": [
          272,
          278
        ]
      },
      {
        "song_title": "For No One",
        "artist": "Beatles",
        "output_uri": "s3://jsmith-output/Beatles/Complete Scores (2)/Songs/John Lennon & Paul Mccartney - For No One.pdf",
        "file_size_bytes": 252125,
        "page_range": [
          278,
          282
        ]
      },
      {
        "song_title": "For You Blue",
        "artist": "Beatles",
        "output_uri": "s3://jsmith-output/Beatles/Complete Scores (2)/Songs/George Harrison - For You Blue.pdf",
        "file_size_bytes": 317462,
        "page_range": [
          282,
          287
        ]
      },
      {
        "song_title": "From Me To You",
        "artist": "Beatles",
        "output_uri": "s3://jsmith-output/Beatles/Complete Scores (2)/Songs/John Lennon & Paul Mccartney - From Me To You.pdf",
        "file_size_bytes": 245981,
        "page_range": [
          287,
          291
        ]
      },
      {
        "song_title": "Get Back",
        "artist": "Beatles",
        "output_uri": "s3://jsmith-output/Beatles/Complete Scores (2)/Songs/John Lennon & Paul Mccartney - Get Back.pdf",
        "file_size_bytes": 513215,
        "page_range": [
          291,
          298
        ]
      },
      {
        "song_title": "Getting Better",
        "artist": "Beatles",
        "output_uri": "s3://jsmith-output/Beatles/Complete Scores (2)/Songs/John Lennon & Paul Mccartney - Getting Better.pdf",
        "file_size_bytes": 578661,
        "page_range": [
          298,
          307
        ]
      },
      {
        "song_title": "Girl",
        "artist": "Beatles",
        "output_uri": "s3://jsmith-output/Beatles/Complete Scores (2)/Songs/John Lennon, Paul Mccartney - Girl.pdf",
        "file_size_bytes": 308481,
        "page_range": [
          307,
          312
        ]
      },
      {
        "song_title": "Glass Onion",
        "artist": "Beatles",
        "output_uri": "s3://jsmith-output/Beatles/Complete Scores (2)/Songs/John Lennon & Paul Mccartney - Glass Onion.pdf",
        "file_size_bytes": 279198,
        "page_range": [
          312,
          316
        ]
      },
      {
        "song_title": "Golden Slumbers",
        "artist": "Beatles",
        "output_uri": "s3://jsmith-output/Beatles/Complete Scores (2)/Songs/John Lennon & Paul Mccartney - Golden Slumbers.pdf",
        "file_size_bytes": 183566,
        "page_range": [
          316,
          319
        ]
      },
      {
        "song_title": "Good Day Sunshine",
        "artist": "Beatles",
        "output_uri": "s3://jsmith-output/Beatles/Complete Scores (2)/Songs/John Lennon & Paul Mccartney - Good Day Sunshine.pdf",
        "file_size_bytes": 377990,
        "page_range": [
          319,
          325
        ]
      },
      {
        "song_title": "Good Morning Good Morning",
        "artist": "Beatles",
        "output_uri": "s3://jsmith-output/Beatles/Complete Scores (2)/Songs/John Lennon & Paul Mccartney - Good Morning Good Morning.pdf",
        "file_size_bytes": 482839,
        "page_range": [
          325,
          332
        ]
      },
      {
        "song_title": "Goodnight",
        "artist": "Beatles",
        "output_uri": "s3://jsmith-output/Beatles/Complete Scores (2)/Songs/John Lennon & Paul Mccartney - Goodnight.pdf",
        "file_size_bytes": 297292,
        "page_range": [
          332,
          337
        ]
      },
      {
        "song_title": "Got to Get You Into My Life",
        "artist": "Beatles",
        "output_uri": "s3://jsmith-output/Beatles/Complete Scores (2)/Songs/John Lennon & Paul Mccartney - Got To Get You Into My Life.pdf",
        "file_size_bytes": 353155,
        "page_range": [
          337,
          343
        ]
      },
      {
        "song_title": "Happiness Is a Warm Gun",
        "artist": "Beatles",
        "output_uri": "s3://jsmith-output/Beatles/Complete Scores (2)/Songs/John Lennon & Paul Mccartney - Happiness Is A Warm Gun.pdf",
        "file_size_bytes": 417659,
        "page_range": [
          343,
          349
        ]
      },
      {
        "song_title": "A Hard Day's Night",
        "artist": "Beatles",
        "output_uri": "s3://jsmith-output/Beatles/Complete Scores (2)/Songs/John Lennon & Paul Mccartney - A Hard Day's Night.pdf",
        "file_size_bytes": 399199,
        "page_range": [
          349,
          355
        ]
      },
      {
        "song_title": "Hello Goodbye",
        "artist": "Beatles",
        "output_uri": "s3://jsmith-output/Beatles/Complete Scores (2)/Songs/John Lennon & Paul Mccartney - Hello Goodbye.pdf",
        "file_size_bytes": 403251,
        "page_range": [
          355,
          361
        ]
      },
      {
        "song_title": "Help!",
        "artist": "Beatles",
        "output_uri": "s3://jsmith-output/Beatles/Complete Scores (2)/Songs/Words & Music By John Lennon & Paul Mccartney - Help!.pdf",
        "file_size_bytes": 375773,
        "page_range": [
          361,
          367
        ]
      },
      {
        "song_title": "Helter Skelter",
        "artist": "Beatles",
        "output_uri": "s3://jsmith-output/Beatles/Complete Scores (2)/Songs/John Lennon & Paul Mccartney - Helter Skelter.pdf",
        "file_size_bytes": 541455,
        "page_range": [
          367,
          375
        ]
      },
      {
        "song_title": "Here Comes the Sun",
        "artist": "Beatles",
        "output_uri": "s3://jsmith-output/Beatles/Complete Scores (2)/Songs/George Harrison - Here Comes The Sun.pdf",
        "file_size_bytes": 477220,
        "page_range": [
          375,
          382
        ]
      },
      {
        "song_title": "Here, There and Everywhere",
        "artist": "Beatles",
        "output_uri": "s3://jsmith-output/Beatles/Complete Scores (2)/Songs/John Lennon & Paul Mccartney - Here, There And Everywhere.pdf",
        "file_size_bytes": 250999,
        "page_range": [
          382,
          386
        ]
      },
      {
        "song_title": "Her Majesty",
        "artist": "Beatles",
        "output_uri": "s3://jsmith-output/Beatles/Complete Scores (2)/Songs/John Lennon & Paul Mccartney - Her Majesty.pdf",
        "file_size_bytes": 125472,
        "page_range": [
          386,
          388
        ]
      },
      {
        "song_title": "Hey Bulldog",
        "artist": "Beatles",
        "output_uri": "s3://jsmith-output/Beatles/Complete Scores (2)/Songs/John Lennon & Paul Mccartney - Hey Bulldog.pdf",
        "file_size_bytes": 320076,
        "page_range": [
          388,
          393
        ]
      },
      {
        "song_title": "Hey Jude",
        "artist": "Beatles",
        "output_uri": "s3://jsmith-output/Beatles/Complete Scores (2)/Songs/Words & Music By John Lennon & Paul Mccartney - Hey Jude.pdf",
        "file_size_bytes": 359687,
        "page_range": [
          393,
          398
        ]
      },
      {
        "song_title": "Hold Me Tight",
        "artist": "Beatles",
        "output_uri": "s3://jsmith-output/Beatles/Complete Scores (2)/Songs/John Lennon & Paul Mccartney - Hold Me Tight.pdf",
        "file_size_bytes": 198090,
        "page_range": [
          398,
          401
        ]
      },
      {
        "song_title": "Honey Don't",
        "artist": "Beatles",
        "output_uri": "s3://jsmith-output/Beatles/Complete Scores (2)/Songs/Carl Lee Perkins - Honey Don't.pdf",
        "file_size_bytes": 424111,
        "page_range": [
          401,
          408
        ]
      },
      {
        "song_title": "Honey Pie",
        "artist": "Beatles",
        "output_uri": "s3://jsmith-output/Beatles/Complete Scores (2)/Songs/John Lennon & Paul Mccartney - Honey Pie.pdf",
        "file_size_bytes": 446106,
        "page_range": [
          408,
          415
        ]
      },
      {
        "song_title": "I Am the Walrus",
        "artist": "Beatles",
        "output_uri": "s3://jsmith-output/Beatles/Complete Scores (2)/Songs/Words & Music By John Lennon & Paul Mccartney - I Am The Walrus.pdf",
        "file_size_bytes": 463994,
        "page_range": [
          415,
          422
        ]
      },
      {
        "song_title": "I Call Your Name",
        "artist": "Beatles",
        "output_uri": "s3://jsmith-output/Beatles/Complete Scores (2)/Songs/John Lennon & Paul Mccartney - I Call Your Name.pdf",
        "file_size_bytes": 326642,
        "page_range": [
          422,
          427
        ]
      },
      {
        "song_title": "I Don't Want to Spoil the Party",
        "artist": "Beatles",
        "output_uri": "s3://jsmith-output/Beatles/Complete Scores (2)/Songs/John Lennon & Paul Mccartney - I Don't Want To Spoil The Party.pdf",
        "file_size_bytes": 352895,
        "page_range": [
          427,
          433
        ]
      },
      {
        "song_title": "I Feel Fine",
        "artist": "Beatles",
        "output_uri": "s3://jsmith-output/Beatles/Complete Scores (2)/Songs/John Lennon, Paul Mccartney - I Feel Fine.pdf",
        "file_size_bytes": 388065,
        "page_range": [
          433,
          439
        ]
      },
      {
        "song_title": "If I Fell",
        "artist": "Beatles",
        "output_uri": "s3://jsmith-output/Beatles/Complete Scores (2)/Songs/John Lennon And Paul Mccartney - If I Fell.pdf",
        "file_size_bytes": 241814,
        "page_range": [
          439,
          443
        ]
      },
      {
        "song_title": "If I Needed Someone",
        "artist": "Beatles",
        "output_uri": "s3://jsmith-output/Beatles/Complete Scores (2)/Songs/George Harrison - If I Needed Someone.pdf",
        "file_size_bytes": 400708,
        "page_range": [
          443,
          449
        ]
      },
      {
        "song_title": "I'll Be Back",
        "artist": "Beatles",
        "output_uri": "s3://jsmith-output/Beatles/Complete Scores (2)/Songs/John Lennon & Paul Mccartney - I'll Be Back.pdf",
        "file_size_bytes": 252891,
        "page_range": [
          449,
          453
        ]
      },
      {
        "song_title": "I'll Cry Instead",
        "artist": "Beatles",
        "output_uri": "s3://jsmith-output/Beatles/Complete Scores (2)/Songs/John Lennon & Paul Mccartney - I'll Cry Instead.pdf",
        "file_size_bytes": 258502,
        "page_range": [
          453,
          457
        ]
      },
      {
        "song_title": "I'll Follow the Sun",
        "artist": "Beatles",
        "output_uri": "s3://jsmith-output/Beatles/Complete Scores (2)/Songs/John Lennon & Paul Mccartney - I'll Follow The Sun.pdf",
        "file_size_bytes": 258041,
        "page_range": [
          457,
          461
        ]
      },
      {
        "song_title": "I'll Get You",
        "artist": "Beatles",
        "output_uri": "s3://jsmith-output/Beatles/Complete Scores (2)/Songs/John Lennon & Paul Mccartney - I'll Get You.pdf",
        "file_size_bytes": 240865,
        "page_range": [
          461,
          465
        ]
      },
      {
        "song_title": "I'm a Loser",
        "artist": "Beatles",
        "output_uri": "s3://jsmith-output/Beatles/Complete Scores (2)/Songs/John Lennon & Paul Mccartney - I'm A Loser.pdf",
        "file_size_bytes": 295551,
        "page_range": [
          465,
          470
        ]
      },
      {
        "song_title": "I'm Down",
        "artist": "Beatles",
        "output_uri": "s3://jsmith-output/Beatles/Complete Scores (2)/Songs/John Lennon & Paul Mccartney - I'm Down.pdf",
        "file_size_bytes": 378359,
        "page_range": [
          470,
          476
        ]
      },
      {
        "song_title": "I Me Mine",
        "artist": "Beatles",
        "output_uri": "s3://jsmith-output/Beatles/Complete Scores (2)/Songs/George Harrison - I Me Mine.pdf",
        "file_size_bytes": 274080,
        "page_range": [
          476,
          480
        ]
      },
      {
        "song_title": "I'M HAPPY JUST TO DANCE WITH YOU",
        "artist": "Beatles",
        "output_uri": "s3://jsmith-output/Beatles/Complete Scores (2)/Songs/Words & Music By John Lennon & Paul Mccartney - I'm Happy Just To Dance With You.pdf",
        "file_size_bytes": 276022,
        "page_range": [
          480,
          484
        ]
      },
      {
        "song_title": "I'm Looking Through You",
        "artist": "Beatles",
        "output_uri": "s3://jsmith-output/Beatles/Complete Scores (2)/Songs/John Lennon & Paul Mccartney - I'm Looking Through You.pdf",
        "file_size_bytes": 347370,
        "page_range": [
          484,
          489
        ]
      },
      {
        "song_title": "I'm Only Sleeping",
        "artist": "Beatles",
        "output_uri": "s3://jsmith-output/Beatles/Complete Scores (2)/Songs/John Lennon & Paul Mccartney - I'm Only Sleeping.pdf",
        "file_size_bytes": 383367,
        "page_range": [
          489,
          495
        ]
      },
      {
        "song_title": "I'm So Tired",
        "artist": "Beatles",
        "output_uri": "s3://jsmith-output/Beatles/Complete Scores (2)/Songs/John Lennon & Paul Mccartney - I'm So Tired.pdf",
        "file_size_bytes": 221446,
        "page_range": [
          495,
          498
        ]
      },
      {
        "song_title": "I Need You",
        "artist": "Beatles",
        "output_uri": "s3://jsmith-output/Beatles/Complete Scores (2)/Songs/George Harrison - I Need You.pdf",
        "file_size_bytes": 270556,
        "page_range": [
          498,
          502
        ]
      },
      {
        "song_title": "In My Life",
        "artist": "Beatles",
        "output_uri": "s3://jsmith-output/Beatles/Complete Scores (2)/Songs/John Lennon & Paul Mccartney - In My Life.pdf",
        "file_size_bytes": 341478,
        "page_range": [
          502,
          507
        ]
      },
      {
        "song_title": "The Inner Light",
        "artist": "Beatles",
        "output_uri": "s3://jsmith-output/Beatles/Complete Scores (2)/Songs/George Harrison - The Inner Light.pdf",
        "file_size_bytes": 249615,
        "page_range": [
          507,
          511
        ]
      },
      {
        "song_title": "I Saw Her Standing There",
        "artist": "Beatles",
        "output_uri": "s3://jsmith-output/Beatles/Complete Scores (2)/Songs/John Lennon & Paul Mccartney - I Saw Her Standing There.pdf",
        "file_size_bytes": 399385,
        "page_range": [
          511,
          517
        ]
      },
      {
        "song_title": "I Should Have Known Better",
        "artist": "Beatles",
        "output_uri": "s3://jsmith-output/Beatles/Complete Scores (2)/Songs/John Lennon & Paul Mccartney - I Should Have Known Better.pdf",
        "file_size_bytes": 378107,
        "page_range": [
          517,
          523
        ]
      },
      {
        "song_title": "It's All Too Much",
        "artist": "Beatles",
        "output_uri": "s3://jsmith-output/Beatles/Complete Scores (2)/Songs/George Harrison - It's All Too Much.pdf",
        "file_size_bytes": 435263,
        "page_range": [
          523,
          530
        ]
      },
      {
        "song_title": "It's Only Love",
        "artist": "Beatles",
        "output_uri": "s3://jsmith-output/Beatles/Complete Scores (2)/Songs/John Lennon & Paul Mccartney - It's Only Love.pdf",
        "file_size_bytes": 243059,
        "page_range": [
          530,
          534
        ]
      },
      {
        "song_title": "It Won't Be Long",
        "artist": "Beatles",
        "output_uri": "s3://jsmith-output/Beatles/Complete Scores (2)/Songs/John Lennon & Paul Mccartney - It Won't Be Long.pdf",
        "file_size_bytes": 267800,
        "page_range": [
          534,
          538
        ]
      },
      {
        "song_title": "I've Got a Feeling",
        "artist": "Beatles",
        "output_uri": "s3://jsmith-output/Beatles/Complete Scores (2)/Songs/John Lennon & Paul Mccartney - I've Got A Feeling.pdf",
        "file_size_bytes": 496120,
        "page_range": [
          538,
          545
        ]
      },
      {
        "song_title": "I've Just Seen a Face",
        "artist": "Beatles",
        "output_uri": "s3://jsmith-output/Beatles/Complete Scores (2)/Songs/John Lennon & Paul Mccartney - I've Just Seen A Face.pdf",
        "file_size_bytes": 370170,
        "page_range": [
          545,
          551
        ]
      },
      {
        "song_title": "I Wanna Be Your Man",
        "artist": "Beatles",
        "output_uri": "s3://jsmith-output/Beatles/Complete Scores (2)/Songs/Words & Music By John Lennon & Paul Mccartney - I Wanna Be Your Man.pdf",
        "file_size_bytes": 261146,
        "page_range": [
          551,
          555
        ]
      },
      {
        "song_title": "I Want to Hold Your Hand",
        "artist": "Beatles",
        "output_uri": "s3://jsmith-output/Beatles/Complete Scores (2)/Songs/John Lennon & Paul Mccartney - I Want To Hold Your Hand.pdf",
        "file_size_bytes": 340940,
        "page_range": [
          555,
          560
        ]
      },
      {
        "song_title": "I Want To Tell You",
        "artist": "Beatles",
        "output_uri": "s3://jsmith-output/Beatles/Complete Scores (2)/Songs/George Harrison - I Want To Tell You.pdf",
        "file_size_bytes": 298594,
        "page_range": [
          560,
          565
        ]
      },
      {
        "song_title": "I Want You",
        "artist": "Beatles",
        "output_uri": "s3://jsmith-output/Beatles/Complete Scores (2)/Songs/John Lennon & Paul Mccartney - I Want You.pdf",
        "file_size_bytes": 548633,
        "page_range": [
          565,
          573
        ]
      },
      {
        "song_title": "I Will",
        "artist": "Beatles",
        "output_uri": "s3://jsmith-output/Beatles/Complete Scores (2)/Songs/John Lennon & Paul Mccartney - I Will.pdf",
        "file_size_bytes": 250519,
        "page_range": [
          573,
          577
        ]
      },
      {
        "song_title": "Julia",
        "artist": "Beatles",
        "output_uri": "s3://jsmith-output/Beatles/Complete Scores (2)/Songs/John Lennon & Paul Mccartney - Julia.pdf",
        "file_size_bytes": 202232,
        "page_range": [
          577,
          580
        ]
      },
      {
        "song_title": "Kansas City",
        "artist": "Beatles",
        "output_uri": "s3://jsmith-output/Beatles/Complete Scores (2)/Songs/Jerry Leiber & Mike Stoller - Kansas City.pdf",
        "file_size_bytes": 536512,
        "page_range": [
          580,
          588
        ]
      },
      {
        "song_title": "Lady Madonna",
        "artist": "Beatles",
        "output_uri": "s3://jsmith-output/Beatles/Complete Scores (2)/Songs/John Lennon & Paul Mccartney - Lady Madonna.pdf",
        "file_size_bytes": 346351,
        "page_range": [
          588,
          593
        ]
      },
      {
        "song_title": "Let It Be",
        "artist": "Beatles",
        "output_uri": "s3://jsmith-output/Beatles/Complete Scores (2)/Songs/John Lennon & Paul Mccartney - Let It Be.pdf",
        "file_size_bytes": 417773,
        "page_range": [
          593,
          599
        ]
      },
      {
        "song_title": "Little Child",
        "artist": "Beatles",
        "output_uri": "s3://jsmith-output/Beatles/Complete Scores (2)/Songs/John Lennon & Paul Mccartney - Little Child.pdf",
        "file_size_bytes": 334867,
        "page_range": [
          599,
          604
        ]
      },
      {
        "song_title": "The Long and Winding Road",
        "artist": "Beatles",
        "output_uri": "s3://jsmith-output/Beatles/Complete Scores (2)/Songs/Words & Music By John Lennon & Paul Mccartney - The Long And Winding Road.pdf",
        "file_size_bytes": 267969,
        "page_range": [
          604,
          608
        ]
      },
      {
        "song_title": "Long Long Long",
        "artist": "Beatles",
        "output_uri": "s3://jsmith-output/Beatles/Complete Scores (2)/Songs/George Harrison - Long Long Long.pdf",
        "file_size_bytes": 249403,
        "page_range": [
          608,
          612
        ]
      },
      {
        "song_title": "Long Tall Sally",
        "artist": "Beatles",
        "output_uri": "s3://jsmith-output/Beatles/Complete Scores (2)/Songs/Words & Music By Ernie Johnson, Richard Penniman & Robert Blackwell - Long Tall Sally.pdf",
        "file_size_bytes": 495637,
        "page_range": [
          612,
          619
        ]
      },
      {
        "song_title": "Lovely Rita",
        "artist": "Beatles",
        "output_uri": "s3://jsmith-output/Beatles/Complete Scores (2)/Songs/John Lennon, Paul Mccartney - Lovely Rita.pdf",
        "file_size_bytes": 410036,
        "page_range": [
          619,
          625
        ]
      },
      {
        "song_title": "Love Me Do",
        "artist": "Beatles",
        "output_uri": "s3://jsmith-output/Beatles/Complete Scores (2)/Songs/John Lennon & Paul Mccartney - Love Me Do.pdf",
        "file_size_bytes": 288967,
        "page_range": [
          625,
          630
        ]
      },
      {
        "song_title": "Love You To",
        "artist": "Beatles",
        "output_uri": "s3://jsmith-output/Beatles/Complete Scores (2)/Songs/George Harrison - Love You To.pdf",
        "file_size_bytes": 339184,
        "page_range": [
          630,
          636
        ]
      },
      {
        "song_title": "Lucy in the Sky with Diamonds",
        "artist": "Beatles",
        "output_uri": "s3://jsmith-output/Beatles/Complete Scores (2)/Songs/John Lennon & Paul Mccartney - Lucy In The Sky With Diamonds.pdf",
        "file_size_bytes": 311357,
        "page_range": [
          636,
          641
        ]
      },
      {
        "song_title": "Maggie Mae",
        "artist": "Beatles",
        "output_uri": "s3://jsmith-output/Beatles/Complete Scores (2)/Songs/Arranged By John Lennon, Paul Mccartney, George Harrison & Richard Starkey - Maggie Mae.pdf",
        "file_size_bytes": 186226,
        "page_range": [
          641,
          644
        ]
      },
      {
        "song_title": "Magical Mystery Tour",
        "artist": "Beatles",
        "output_uri": "s3://jsmith-output/Beatles/Complete Scores (2)/Songs/Words & Music By John Lennon & Paul Mccartney - Magical Mystery Tour.pdf",
        "file_size_bytes": 504145,
        "page_range": [
          644,
          652
        ]
      },
      {
        "song_title": "Martha My Dear",
        "artist": "Beatles",
        "output_uri": "s3://jsmith-output/Beatles/Complete Scores (2)/Songs/John Lennon & Paul Mccartney - Martha My Dear.pdf",
        "file_size_bytes": 344452,
        "page_range": [
          652,
          657
        ]
      },
      {
        "song_title": "Matchbox",
        "artist": "Beatles",
        "output_uri": "s3://jsmith-output/Beatles/Complete Scores (2)/Songs/Carl Lee Perkins - Matchbox.pdf",
        "file_size_bytes": 268324,
        "page_range": [
          657,
          661
        ]
      },
      {
        "song_title": "Maxwell's Silver Hammer",
        "artist": "Beatles",
        "output_uri": "s3://jsmith-output/Beatles/Complete Scores (2)/Songs/John Lennon & Paul Mccartney - Maxwell's Silver Hammer.pdf",
        "file_size_bytes": 337589,
        "page_range": [
          661,
          666
        ]
      },
      {
        "song_title": "Mean Mr. Mustard",
        "artist": "Beatles",
        "output_uri": "s3://jsmith-output/Beatles/Complete Scores (2)/Songs/John Lennon & Paul Mccartney - Mean Mr. Mustard.pdf",
        "file_size_bytes": 187183,
        "page_range": [
          666,
          669
        ]
      },
      {
        "song_title": "Michelle",
        "artist": "Beatles",
        "output_uri": "s3://jsmith-output/Beatles/Complete Scores (2)/Songs/Words & Music By John Lennon & Paul Mccartney - Michelle.pdf",
        "file_size_bytes": 364778,
        "page_range": [
          669,
          675
        ]
      },
      {
        "song_title": "Misery",
        "artist": "Beatles",
        "output_uri": "s3://jsmith-output/Beatles/Complete Scores (2)/Songs/John Lennon & Paul Mccartney - Misery.pdf",
        "file_size_bytes": 246601,
        "page_range": [
          675,
          679
        ]
      },
      {
        "song_title": "Money (That's What I Want)",
        "artist": "Beatles",
        "output_uri": "s3://jsmith-output/Beatles/Complete Scores (2)/Songs/Berry Gordy Junior & Janie Bradford - Money (that's What I Want).pdf",
        "file_size_bytes": 359187,
        "page_range": [
          679,
          684
        ]
      },
      {
        "song_title": "Mother Nature's Son",
        "artist": "Beatles",
        "output_uri": "s3://jsmith-output/Beatles/Complete Scores (2)/Songs/John Lennon & Paul Mccartney - Mother Nature's Son.pdf",
        "file_size_bytes": 195952,
        "page_range": [
          684,
          687
        ]
      },
      {
        "song_title": "Mr. Moonlight",
        "artist": "Beatles",
        "output_uri": "s3://jsmith-output/Beatles/Complete Scores (2)/Songs/Words & Music By Ray Lee Johnson - Mr. Moonlight.pdf",
        "file_size_bytes": 375400,
        "page_range": [
          687,
          693
        ]
      },
      {
        "song_title": "The Night Before",
        "artist": "Beatles",
        "output_uri": "s3://jsmith-output/Beatles/Complete Scores (2)/Songs/John Lennon & Paul Mccartney - The Night Before.pdf",
        "file_size_bytes": 385917,
        "page_range": [
          693,
          699
        ]
      },
      {
        "song_title": "No Reply",
        "artist": "Beatles",
        "output_uri": "s3://jsmith-output/Beatles/Complete Scores (2)/Songs/John Lennon & Paul Mccartney - No Reply.pdf",
        "file_size_bytes": 196793,
        "page_range": [
          699,
          702
        ]
      },
      {
        "song_title": "Norwegian Wood",
        "artist": "Beatles",
        "output_uri": "s3://jsmith-output/Beatles/Complete Scores (2)/Songs/John Lennon & Paul Mccartney - Norwegian Wood.pdf",
        "file_size_bytes": 271391,
        "page_range": [
          702,
          706
        ]
      },
      {
        "song_title": "Not a Second Time",
        "artist": "Beatles",
        "output_uri": "s3://jsmith-output/Beatles/Complete Scores (2)/Songs/John Lennon & Paul Mccartney - Not A Second Time.pdf",
        "file_size_bytes": 263943,
        "page_range": [
          706,
          710
        ]
      },
      {
        "song_title": "Nowhere Man",
        "artist": "Beatles",
        "output_uri": "s3://jsmith-output/Beatles/Complete Scores (2)/Songs/John Lennon & Paul Mccartney - Nowhere Man.pdf",
        "file_size_bytes": 329747,
        "page_range": [
          710,
          715
        ]
      },
      {
        "song_title": "Ob-la-di Ob-la-da",
        "artist": "Beatles",
        "output_uri": "s3://jsmith-output/Beatles/Complete Scores (2)/Songs/John Lennon & Paul Mccartney - Ob-la-di Ob-la-da.pdf",
        "file_size_bytes": 329021,
        "page_range": [
          715,
          720
        ]
      },
      {
        "song_title": "Octopus's Garden",
        "artist": "Beatles",
        "output_uri": "s3://jsmith-output/Beatles/Complete Scores (2)/Songs/Ringo Starr - Octopus's Garden.pdf",
        "file_size_bytes": 338148,
        "page_range": [
          720,
          725
        ]
      },
      {
        "song_title": "Oh! Darling",
        "artist": "Beatles",
        "output_uri": "s3://jsmith-output/Beatles/Complete Scores (2)/Songs/John Lennon & Paul Mccartney - Oh! Darling.pdf",
        "file_size_bytes": 344404,
        "page_range": [
          725,
          730
        ]
      },
      {
        "song_title": "Old Brown Shoe",
        "artist": "Beatles",
        "output_uri": "s3://jsmith-output/Beatles/Complete Scores (2)/Songs/George Harrison - Old Brown Shoe.pdf",
        "file_size_bytes": 469987,
        "page_range": [
          730,
          737
        ]
      },
      {
        "song_title": "One After 909",
        "artist": "Beatles",
        "output_uri": "s3://jsmith-output/Beatles/Complete Scores (2)/Songs/Words & Music By John Lennon & Paul Mccartney - One After 909.pdf",
        "file_size_bytes": 605694,
        "page_range": [
          737,
          746
        ]
      },
      {
        "song_title": "Only a Northern Song",
        "artist": "Beatles",
        "output_uri": "s3://jsmith-output/Beatles/Complete Scores (2)/Songs/George Harrison - Only A Northern Song.pdf",
        "file_size_bytes": 371146,
        "page_range": [
          746,
          752
        ]
      },
      {
        "song_title": "Paperback Writer",
        "artist": "Beatles",
        "output_uri": "s3://jsmith-output/Beatles/Complete Scores (2)/Songs/Words & Music By John Lennon & Paul Mccartney - Paperback Writer.pdf",
        "file_size_bytes": 312598,
        "page_range": [
          752,
          757
        ]
      },
      {
        "song_title": "Penny Lane",
        "artist": "Beatles",
        "output_uri": "s3://jsmith-output/Beatles/Complete Scores (2)/Songs/Words & Music By John Lennon & Paul Mccartney - Penny Lane.pdf",
        "file_size_bytes": 364796,
        "page_range": [
          757,
          763
        ]
      },
      {
        "song_title": "Piggies",
        "artist": "Beatles",
        "output_uri": "s3://jsmith-output/Beatles/Complete Scores (2)/Songs/George Harrison - Piggies.pdf",
        "file_size_bytes": 257053,
        "page_range": [
          763,
          767
        ]
      },
      {
        "song_title": "Please Mr. Postman",
        "artist": "Beatles",
        "output_uri": "s3://jsmith-output/Beatles/Complete Scores (2)/Songs/Words & Music By B. Holland & F.c. Gorman - Please Mr. Postman.pdf",
        "file_size_bytes": 328433,
        "page_range": [
          767,
          772
        ]
      },
      {
        "song_title": "Please Please Me",
        "artist": "Beatles",
        "output_uri": "s3://jsmith-output/Beatles/Complete Scores (2)/Songs/John Lennon & Paul Mccartney - Please Please Me.pdf",
        "file_size_bytes": 267293,
        "page_range": [
          772,
          776
        ]
      },
      {
        "song_title": "Polythene Pam",
        "artist": "Beatles",
        "output_uri": "s3://jsmith-output/Beatles/Complete Scores (2)/Songs/John Lennon & Paul Mccartney - Polythene Pam.pdf",
        "file_size_bytes": 309352,
        "page_range": [
          776,
          781
        ]
      },
      {
        "song_title": "P.S. I Love You",
        "artist": "Beatles",
        "output_uri": "s3://jsmith-output/Beatles/Complete Scores (2)/Songs/Words & Music By John Lennon & Paul Mccartney - P.s. I Love You.pdf",
        "file_size_bytes": 195002,
        "page_range": [
          781,
          784
        ]
      },
      {
        "song_title": "Rain",
        "artist": "Beatles",
        "output_uri": "s3://jsmith-output/Beatles/Complete Scores (2)/Songs/John Lennon & Paul Mccartney - Rain.pdf",
        "file_size_bytes": 399854,
        "page_range": [
          784,
          790
        ]
      },
      {
        "song_title": "Revolution",
        "artist": "Beatles",
        "output_uri": "s3://jsmith-output/Beatles/Complete Scores (2)/Songs/John Lennon & Paul Mccartney - Revolution.pdf",
        "file_size_bytes": 465772,
        "page_range": [
          790,
          797
        ]
      },
      {
        "song_title": "Revolution 1",
        "artist": "Beatles",
        "output_uri": "s3://jsmith-output/Beatles/Complete Scores (2)/Songs/John Lennon & Paul Mccartney - Revolution 1.pdf",
        "file_size_bytes": 489548,
        "page_range": [
          797,
          804
        ]
      },
      {
        "song_title": "Revolution 9",
        "artist": "Beatles",
        "output_uri": "s3://jsmith-output/Beatles/Complete Scores (2)/Songs/John Lennon & Paul Mccartney - Revolution 9.pdf",
        "file_size_bytes": 581967,
        "page_range": [
          804,
          814
        ]
      },
      {
        "song_title": "Rock and Roll Music",
        "artist": "Beatles",
        "output_uri": "s3://jsmith-output/Beatles/Complete Scores (2)/Songs/Chuck Berry - Rock And Roll Music.pdf",
        "file_size_bytes": 183872,
        "page_range": [
          814,
          817
        ]
      },
      {
        "song_title": "Rocky Raccoon",
        "artist": "Beatles",
        "output_uri": "s3://jsmith-output/Beatles/Complete Scores (2)/Songs/John Lennon & Paul Mccartney - Rocky Raccoon.pdf",
        "file_size_bytes": 394134,
        "page_range": [
          817,
          823
        ]
      },
      {
        "song_title": "Roll Over Beethoven",
        "artist": "Beatles",
        "output_uri": "s3://jsmith-output/Beatles/Complete Scores (2)/Songs/Chuck Berry - Roll Over Beethoven.pdf",
        "file_size_bytes": 476391,
        "page_range": [
          823,
          830
        ]
      },
      {
        "song_title": "Run For Your Life",
        "artist": "Beatles",
        "output_uri": "s3://jsmith-output/Beatles/Complete Scores (2)/Songs/John Lennon & Paul Mccartney - Run For Your Life.pdf",
        "file_size_bytes": 357299,
        "page_range": [
          830,
          836
        ]
      },
      {
        "song_title": "Savoy Truffle",
        "artist": "Beatles",
        "output_uri": "s3://jsmith-output/Beatles/Complete Scores (2)/Songs/George Harrison - Savoy Truffle.pdf",
        "file_size_bytes": 418221,
        "page_range": [
          836,
          842
        ]
      },
      {
        "song_title": "Sexy Sadie",
        "artist": "Beatles",
        "output_uri": "s3://jsmith-output/Beatles/Complete Scores (2)/Songs/John Lennon & Paul Mccartney - Sexy Sadie.pdf",
        "file_size_bytes": 276845,
        "page_range": [
          842,
          846
        ]
      },
      {
        "song_title": "Sgt. Pepper's Lonely Hearts Club Band",
        "artist": "Beatles",
        "output_uri": "s3://jsmith-output/Beatles/Complete Scores (2)/Songs/John Lennon & Paul Mccartney - Sgt. Pepper's Lonely Hearts Club Band.pdf",
        "file_size_bytes": 330960,
        "page_range": [
          846,
          851
        ]
      },
      {
        "song_title": "Sgt. Pepper's Lonely Hearts Club Band (Reprise)",
        "artist": "Beatles",
        "output_uri": "s3://jsmith-output/Beatles/Complete Scores (2)/Songs/John Lennon & Paul Mccartney - Sgt. Pepper's Lonely Hearts Club Band (reprise).pdf",
        "file_size_bytes": 253276,
        "page_range": [
          851,
          855
        ]
      },
      {
        "song_title": "She Came In Through The Bathroom Window",
        "artist": "Beatles",
        "output_uri": "s3://jsmith-output/Beatles/Complete Scores (2)/Songs/John Lennon & Paul Mccartney - She Came In Through The Bathroom Window.pdf",
        "file_size_bytes": 201784,
        "page_range": [
          855,
          858
        ]
      },
      {
        "song_title": "She Loves You",
        "artist": "Beatles",
        "output_uri": "s3://jsmith-output/Beatles/Complete Scores (2)/Songs/Words & Music By John Lennon & Paul Mccartney - She Loves You.pdf",
        "file_size_bytes": 300987,
        "page_range": [
          858,
          863
        ]
      },
      {
        "song_title": "She Said She Said",
        "artist": "Beatles",
        "output_uri": "s3://jsmith-output/Beatles/Complete Scores (2)/Songs/John Lennon & Paul Mccartney - She Said She Said.pdf",
        "file_size_bytes": 273127,
        "page_range": [
          863,
          867
        ]
      },
      {
        "song_title": "She's a Woman",
        "artist": "Beatles",
        "output_uri": "s3://jsmith-output/Beatles/Complete Scores (2)/Songs/John Lennon & Paul Mccartney - She's A Woman.pdf",
        "file_size_bytes": 427683,
        "page_range": [
          867,
          874
        ]
      },
      {
        "song_title": "She's Leaving Home",
        "artist": "Beatles",
        "output_uri": "s3://jsmith-output/Beatles/Complete Scores (2)/Songs/John Lennon & Paul Mccartney - She's Leaving Home.pdf",
        "file_size_bytes": 750968,
        "page_range": [
          874,
          887
        ]
      },
      {
        "song_title": "Slow Down",
        "artist": "Beatles",
        "output_uri": "s3://jsmith-output/Beatles/Complete Scores (2)/Songs/Larry Williams - Slow Down.pdf",
        "file_size_bytes": 519198,
        "page_range": [
          887,
          895
        ]
      },
      {
        "song_title": "Something",
        "artist": "Beatles",
        "output_uri": "s3://jsmith-output/Beatles/Complete Scores (2)/Songs/George Harrison - Something.pdf",
        "file_size_bytes": 285545,
        "page_range": [
          895,
          899
        ]
      },
      {
        "song_title": "Strawberry Fields Forever",
        "artist": "Beatles",
        "output_uri": "s3://jsmith-output/Beatles/Complete Scores (2)/Songs/John Lennon & Paul Mccartney - Strawberry Fields Forever.pdf",
        "file_size_bytes": 365114,
        "page_range": [
          899,
          905
        ]
      },
      {
        "song_title": "Sun King",
        "artist": "Beatles",
        "output_uri": "s3://jsmith-output/Beatles/Complete Scores (2)/Songs/John Lennon & Paul Mccartney - Sun King.pdf",
        "file_size_bytes": 252730,
        "page_range": [
          905,
          909
        ]
      },
      {
        "song_title": "A Taste of Honey",
        "artist": "Beatles",
        "output_uri": "s3://jsmith-output/Beatles/Complete Scores (2)/Songs/Ric Marlow, Music By Bobby Scott - A Taste Of Honey.pdf",
        "file_size_bytes": 188598,
        "page_range": [
          909,
          912
        ]
      },
      {
        "song_title": "Taxman",
        "artist": "Beatles",
        "output_uri": "s3://jsmith-output/Beatles/Complete Scores (2)/Songs/George Harrison - Taxman.pdf",
        "file_size_bytes": 380030,
        "page_range": [
          912,
          918
        ]
      },
      {
        "song_title": "Tell Me What You See",
        "artist": "Beatles",
        "output_uri": "s3://jsmith-output/Beatles/Complete Scores (2)/Songs/John Lennon & Paul Mccartney - Tell Me What You See.pdf",
        "file_size_bytes": 229514,
        "page_range": [
          918,
          922
        ]
      },
      {
        "song_title": "Tell Me Why",
        "artist": "Beatles",
        "output_uri": "s3://jsmith-output/Beatles/Complete Scores (2)/Songs/John Lennon & Paul Mccartney - Tell Me Why.pdf",
        "file_size_bytes": 304141,
        "page_range": [
          922,
          927
        ]
      },
      {
        "song_title": "Thank You Girl",
        "artist": "Beatles",
        "output_uri": "s3://jsmith-output/Beatles/Complete Scores (2)/Songs/John Lennon & Paul Mccartney - Thank You Girl.pdf",
        "file_size_bytes": 260377,
        "page_range": [
          927,
          931
        ]
      },
      {
        "song_title": "There's a Place",
        "artist": "Beatles",
        "output_uri": "s3://jsmith-output/Beatles/Complete Scores (2)/Songs/John Lennon & Paul Mccartney - There's A Place.pdf",
        "file_size_bytes": 240751,
        "page_range": [
          931,
          935
        ]
      },
      {
        "song_title": "Things We Said Today",
        "artist": "Beatles",
        "output_uri": "s3://jsmith-output/Beatles/Complete Scores (2)/Songs/John Lennon & Paul Mccartney - Things We Said Today.pdf",
        "file_size_bytes": 262060,
        "page_range": [
          935,
          939
        ]
      },
      {
        "song_title": "Think For Yourself",
        "artist": "Beatles",
        "output_uri": "s3://jsmith-output/Beatles/Complete Scores (2)/Songs/George Harrison - Think For Yourself.pdf",
        "file_size_bytes": 360371,
        "page_range": [
          939,
          944
        ]
      },
      {
        "song_title": "This Boy",
        "artist": "Beatles",
        "output_uri": "s3://jsmith-output/Beatles/Complete Scores (2)/Songs/John Lennon & Paul Mccartney - This Boy.pdf",
        "file_size_bytes": 252403,
        "page_range": [
          944,
          948
        ]
      },
      {
        "song_title": "Ticket to Ride",
        "artist": "Beatles",
        "output_uri": "s3://jsmith-output/Beatles/Complete Scores (2)/Songs/John Lennon & Paul Mccartney - Ticket To Ride.pdf",
        "file_size_bytes": 303808,
        "page_range": [
          948,
          953
        ]
      },
      {
        "song_title": "Till There Was You",
        "artist": "Beatles",
        "output_uri": "s3://jsmith-output/Beatles/Complete Scores (2)/Songs/Meredith Willson - Till There Was You.pdf",
        "file_size_bytes": 314119,
        "page_range": [
          953,
          958
        ]
      },
      {
        "song_title": "Tomorrow Never Knows",
        "artist": "Beatles",
        "output_uri": "s3://jsmith-output/Beatles/Complete Scores (2)/Songs/John Lennon & Paul Mccartney - Tomorrow Never Knows.pdf",
        "file_size_bytes": 299869,
        "page_range": [
          958,
          963
        ]
      },
      {
        "song_title": "Twist and Shout",
        "artist": "Beatles",
        "output_uri": "s3://jsmith-output/Beatles/Complete Scores (2)/Songs/Words & Music By Bert Russell & Phil Medley - Twist And Shout.pdf",
        "file_size_bytes": 411912,
        "page_range": [
          963,
          969
        ]
      },
      {
        "song_title": "Two of Us",
        "artist": "Beatles",
        "output_uri": "s3://jsmith-output/Beatles/Complete Scores (2)/Songs/John Lennon & Paul Mccartney - Two Of Us.pdf",
        "file_size_bytes": 312214,
        "page_range": [
          969,
          974
        ]
      },
      {
        "song_title": "Wait",
        "artist": "Beatles",
        "output_uri": "s3://jsmith-output/Beatles/Complete Scores (2)/Songs/John Lennon & Paul Mccartney - Wait.pdf",
        "file_size_bytes": 250994,
        "page_range": [
          974,
          978
        ]
      },
      {
        "song_title": "We Can Work It Out",
        "artist": "Beatles",
        "output_uri": "s3://jsmith-output/Beatles/Complete Scores (2)/Songs/John Lennon & Paul Mccartney - We Can Work It Out.pdf",
        "file_size_bytes": 262397,
        "page_range": [
          978,
          982
        ]
      },
      {
        "song_title": "What Goes On?",
        "artist": "Beatles",
        "output_uri": "s3://jsmith-output/Beatles/Complete Scores (2)/Songs/Words & Music By John Lennon, Paul Mccartney & Richard Starkey - What Goes On-.pdf",
        "file_size_bytes": 409997,
        "page_range": [
          982,
          988
        ]
      },
      {
        "song_title": "What You're Doing",
        "artist": "Beatles",
        "output_uri": "s3://jsmith-output/Beatles/Complete Scores (2)/Songs/John Lennon & Paul Mccartney - What You're Doing.pdf",
        "file_size_bytes": 360767,
        "page_range": [
          988,
          994
        ]
      },
      {
        "song_title": "When I Get Home",
        "artist": "Beatles",
        "output_uri": "s3://jsmith-output/Beatles/Complete Scores (2)/Songs/John Lennon & Paul Mccartney - When I Get Home.pdf",
        "file_size_bytes": 293755,
        "page_range": [
          994,
          999
        ]
      },
      {
        "song_title": "When I'm Sixty Four",
        "artist": "Beatles",
        "output_uri": "s3://jsmith-output/Beatles/Complete Scores (2)/Songs/John Lennon & Paul Mccartney - When I'm Sixty Four.pdf",
        "file_size_bytes": 360526,
        "page_range": [
          999,
          1005
        ]
      },
      {
        "song_title": "While My Guitar Gently Weeps",
        "artist": "Beatles",
        "output_uri": "s3://jsmith-output/Beatles/Complete Scores (2)/Songs/George Harrison - While My Guitar Gently Weeps.pdf",
        "file_size_bytes": 657957,
        "page_range": [
          1005,
          1014
        ]
      },
      {
        "song_title": "Why Don't We Do It in the Road?",
        "artist": "Beatles",
        "output_uri": "s3://jsmith-output/Beatles/Complete Scores (2)/Songs/John Lennon & Paul Mccartney - Why Don't We Do It In The Road-.pdf",
        "file_size_bytes": 190186,
        "page_range": [
          1014,
          1017
        ]
      },
      {
        "song_title": "Wild Honey Pie",
        "artist": "Beatles",
        "output_uri": "s3://jsmith-output/Beatles/Complete Scores (2)/Songs/John Lennon & Paul Mccartney - Wild Honey Pie.pdf",
        "file_size_bytes": 166905,
        "page_range": [
          1017,
          1020
        ]
      },
      {
        "song_title": "With a Little Help From My Friends",
        "artist": "Beatles",
        "output_uri": "s3://jsmith-output/Beatles/Complete Scores (2)/Songs/John Lennon & Paul Mccartney - With A Little Help From My Friends.pdf",
        "file_size_bytes": 449025,
        "page_range": [
          1020,
          1027
        ]
      },
      {
        "song_title": "Within You Without You",
        "artist": "Beatles",
        "output_uri": "s3://jsmith-output/Beatles/Complete Scores (2)/Songs/George Harrison - Within You Without You.pdf",
        "file_size_bytes": 721285,
        "page_range": [
          1027,
          1039
        ]
      },
      {
        "song_title": "The Word",
        "artist": "Beatles",
        "output_uri": "s3://jsmith-output/Beatles/Complete Scores (2)/Songs/John Lennon & Paul Mccartney - The Word.pdf",
        "file_size_bytes": 339217,
        "page_range": [
          1039,
          1044
        ]
      },
      {
        "song_title": "Words of Love",
        "artist": "Beatles",
        "output_uri": "s3://jsmith-output/Beatles/Complete Scores (2)/Songs/Buddy Holly - Words Of Love.pdf",
        "file_size_bytes": 195010,
        "page_range": [
          1044,
          1047
        ]
      },
      {
        "song_title": "Yellow Submarine",
        "artist": "Beatles",
        "output_uri": "s3://jsmith-output/Beatles/Complete Scores (2)/Songs/John Lennon & Paul Mccartney - Yellow Submarine.pdf",
        "file_size_bytes": 343217,
        "page_range": [
          1047,
          1053
        ]
      },
      {
        "song_title": "Yer Blues",
        "artist": "Beatles",
        "output_uri": "s3://jsmith-output/Beatles/Complete Scores (2)/Songs/John Lennon & Paul Mccartney - Yer Blues.pdf",
        "file_size_bytes": 488782,
        "page_range": [
          1053,
          1060
        ]
      },
      {
        "song_title": "Yes It Is",
        "artist": "Beatles",
        "output_uri": "s3://jsmith-output/Beatles/Complete Scores (2)/Songs/John Lennon & Paul Mccartney - Yes It Is.pdf",
        "file_size_bytes": 238024,
        "page_range": [
          1060,
          1064
        ]
      },
      {
        "song_title": "Yesterday",
        "artist": "Beatles",
        "output_uri": "s3://jsmith-output/Beatles/Complete Scores (2)/Songs/John Lennon & Paul Mccartney - Yesterday.pdf",
        "file_size_bytes": 178988,
        "page_range": [
          1064,
          1067
        ]
      },
      {
        "song_title": "You Can't Do That",
        "artist": "Beatles",
        "output_uri": "s3://jsmith-output/Beatles/Complete Scores (2)/Songs/John Lennon & Paul Mccartney - You Can't Do That.pdf",
        "file_size_bytes": 399933,
        "page_range": [
          1067,
          1073
        ]
      },
      {
        "song_title": "You Know My Name (Look Up The Number)",
        "artist": "Beatles",
        "output_uri": "s3://jsmith-output/Beatles/Complete Scores (2)/Songs/Words & Music By John Lennon & Paul Mccartney - You Know My Name (look Up The Number).pdf",
        "file_size_bytes": 554498,
        "page_range": [
          1073,
          1082
        ]
      },
      {
        "song_title": "You Like Me Too Much",
        "artist": "Beatles",
        "output_uri": "s3://jsmith-output/Beatles/Complete Scores (2)/Songs/George Harrison - You Like Me Too Much.pdf",
        "file_size_bytes": 439319,
        "page_range": [
          1082,
          1089
        ]
      },
      {
        "song_title": "You Never Give Me Your Money",
        "artist": "Beatles",
        "output_uri": "s3://jsmith-output/Beatles/Complete Scores (2)/Songs/John Lennon & Paul Mccartney - You Never Give Me Your Money.pdf",
        "file_size_bytes": 526963,
        "page_range": [
          1089,
          1097
        ]
      },
      {
        "song_title": "You're Going to Lose That Girl",
        "artist": "Beatles",
        "output_uri": "s3://jsmith-output/Beatles/Complete Scores (2)/Songs/John Lennon & Paul Mccartney - You're Going To Lose That Girl.pdf",
        "file_size_bytes": 336788,
        "page_range": [
          1097,
          1102
        ]
      },
      {
        "song_title": "Your Mother Should Know",
        "artist": "Beatles",
        "output_uri": "s3://jsmith-output/Beatles/Complete Scores (2)/Songs/Words & Music By John Lennon & Paul Mccartney - Your Mother Should Know.pdf",
        "file_size_bytes": 301870,
        "page_range": [
          1102,
          1107
        ]
      },
      {
        "song_title": "You've Got to Hide Your Love Away",
        "artist": "Beatles",
        "output_uri": "s3://jsmith-output/Beatles/Complete Scores (2)/Songs/John Lennon & Paul Mccartney - You've Got To Hide Your Love Away.pdf",
        "file_size_bytes": 186624,
        "page_range": [
          1107,
          1110
        ]
      },
      {
        "song_title": "You've Really Got a Hold on Me",
        "artist": "Beatles",
        "output_uri": "s3://jsmith-output/Beatles/Complete Scores (2)/Songs/William Robinson - You've Really Got A Hold On Me.pdf",
        "file_size_bytes": 269592,
        "page_range": [
          1110,
          1114
        ]
      },
      {
        "song_title": "You Won't See Me",
        "artist": "Beatles",
        "output_uri": "s3://jsmith-output/Beatles/Complete Scores (2)/Songs/John Lennon & Paul Mccartney - You Won't See Me.pdf",
        "file_size_bytes": 413180,
        "page_range": [
          1114,
          1120
        ]
      }
    ]
  }
}