{
  "book_id": "james-taylor-james-taylor-pvg-book",
  "toc": {
    "entries": [
      {
        "song_title": "Anywhere Like Heaven",
        "page_number": 70,
        "artist": null,
        "confidence": 0.9
      },
      {
        "song_title": "Blossom",
        "page_number": 80,
        "artist": null,
        "confidence": 0.9
      },
      {
        "song_title": "The Blues Is Just A Bad Dream",
        "page_number": 82,
        "artist": null,
        "confidence": 0.9
      },
      {
        "song_title": "Brighten Your Night With My Day",
        "page_number": 49,
        "artist": null,
        "confidence": 0.9
      },
      {
        "song_title": "Carolina In My Mind",
        "page_number": 108,
        "artist": null,
        "confidence": 0.9
      },
      {
        "song_title": "Country Road",
        "page_number": 52,
        "artist": null,
        "confidence": 0.9
      },
      {
        "song_title": "Don't Talk Now",
        "page_number": 60,
        "artist": null,
        "confidence": 0.9
      },
      {
        "song_title": "Fire and Rain",
        "page_number": 34,
        "artist": null,
        "confidence": 0.9
      },
      {
        "song_title": "Knocking 'Round The Zoo",
        "page_number": 88,
        "artist": null,
        "confidence": 0.9
      },
      {
        "song_title": "Lo And Behold",
        "page_number": 94,
        "artist": null,
        "confidence": 0.9
      },
      {
        "song_title": "Night Owl",
        "page_number": 97,
        "artist": null,
        "confidence": 0.9
      },
      {
        "song_title": "Oh Baby Don't Loose Your Lip On Me",
        "page_number": 68,
        "artist": null,
        "confidence": 0.9
      },
      {
        "song_title": "Rainy Day Man",
        "page_number": 84,
        "artist": null,
        "confidence": 0.9
      },
      {
        "song_title": "Something In The Way She Moves",
        "page_number": 44,
        "artist": null,
        "confidence": 0.9
      },
      {
        "song_title": "Something's Wrong",
        "page_number": 72,
        "artist": null,
        "confidence": 0.9
      },
      {
        "song_title": "Steam Roller",
        "page_number": 76,
        "artist": null,
        "confidence": 0.9
      },
      {
        "song_title": "Suite For 20G",
        "page_number": 102,
        "artist": null,
        "confidence": 0.9
      },
      {
        "song_title": "Sunny Skies",
        "page_number": 37,
        "artist": null,
        "confidence": 0.9
      },
      {
        "song_title": "Sunshine, Sunshine",
        "page_number": 64,
        "artist": null,
        "confidence": 0.9
      },
      {
        "song_title": "Sweet Baby James",
        "page_number": 57,
        "artist": null,
        "confidence": 0.9
      },
      {
        "song_title": "Takin' It In",
        "page_number": 40,
        "artist": null,
        "confidence": 0.9
      }
    ],
    "extraction_method": "bedrock_vision",
    "confidence": 0.9,
    "artist_overrides": {}
  },
  "output": {
    "output_files": [
      {
        "song_title": "Fire and Rain",
        "artist": "James Taylor",
        "output_uri": "s3://jsmith-output/James Taylor/James Taylor [pvg Book]/Songs/James Taylor - Fire And Rain.pdf",
        "file_size_bytes": 812029,
        "page_range": [
          2,
          5
        ]
      },
      {
        "song_title": "Sunny Skies",
        "artist": "James Taylor",
        "output_uri": "s3://jsmith-output/James Taylor/James Taylor [pvg Book]/Songs/James Taylor - Sunny Skies.pdf",
        "file_size_bytes": 716883,
        "page_range": [
          5,
          8
        ]
      },
      {
        "song_title": "Takin' It In",
        "artist": "James Taylor",
        "output_uri": "s3://jsmith-output/James Taylor/James Taylor [pvg Book]/Songs/James Taylor - Takin' It In.pdf",
        "file_size_bytes": 1018373,
        "page_range": [
          8,
          12
        ]
      },
      {
        "song_title": "Something In The Way She Moves",
        "artist": "James Taylor",
        "output_uri": "s3://jsmith-output/James Taylor/James Taylor [pvg Book]/Songs/James Taylor - Something In The Way She Moves.pdf",
        "file_size_bytes": 1079711,
        "page_range": [
          12,
          17
        ]
      },
      {
        "song_title": "Brighten Your Night With My Day",
        "artist": "James Taylor",
        "output_uri": "s3://jsmith-output/James Taylor/James Taylor [pvg Book]/Songs/James Taylor - Brighten Your Night With My Day.pdf",
        "file_size_bytes": 766246,
        "page_range": [
          17,
          20
        ]
      },
      {
        "song_title": "Country Road",
        "artist": "James Taylor",
        "output_uri": "s3://jsmith-output/James Taylor/James Taylor [pvg Book]/Songs/James Taylor - Country Road.pdf",
        "file_size_bytes": 1125207,
        "page_range": [
          20,
          25
        ]
      },
      {
        "song_title": "Sweet Baby James",
        "artist": "James Taylor",
        "output_uri": "s3://jsmith-output/James Taylor/James Taylor [pvg Book]/Songs/James Taylor - Sweet Baby James.pdf",
        "file_size_bytes": 722054,
        "page_range": [
          25,
          28
        ]
      },
      {
        "song_title": "Don't Talk Now",
        "artist": "James Taylor",
        "output_uri": "s3://jsmith-output/James Taylor/James Taylor [pvg Book]/Songs/James Taylor - Don't Talk Now.pdf",
        "file_size_bytes": 896927,
        "page_range": [
          28,
          32
        ]
      },
      {
        "song_title": "Sunshine, Sunshine",
        "artist": "James Taylor",
        "output_uri": "s3://jsmith-output/James Taylor/James Taylor [pvg Book]/Songs/James Taylor - Sunshine, Sunshine.pdf",
        "file_size_bytes": 946606,
        "page_range": [
          32,
          36
        ]
      },
      {
        "song_title": "Oh Baby Don't Loose Your Lip On Me",
        "artist": "James Taylor",
        "output_uri": "s3://jsmith-output/James Taylor/James Taylor [pvg Book]/Songs/James Taylor - Oh Baby Don't Loose Your Lip On Me.pdf",
        "file_size_bytes": 510135,
        "page_range": [
          36,
          38
        ]
      },
      {
        "song_title": "Anywhere Like Heaven",
        "artist": "James Taylor",
        "output_uri": "s3://jsmith-output/James Taylor/James Taylor [pvg Book]/Songs/James Taylor - Anywhere Like Heaven.pdf",
        "file_size_bytes": 511221,
        "page_range": [
          38,
          40
        ]
      },
      {
        "song_title": "Something's Wrong",
        "artist": "James Taylor",
        "output_uri": "s3://jsmith-output/James Taylor/James Taylor [pvg Book]/Songs/James Taylor - Something's Wrong.pdf",
        "file_size_bytes": 1007283,
        "page_range": [
          40,
          44
        ]
      },
      {
        "song_title": "Steam Roller",
        "artist": "James Taylor",
        "output_uri": "s3://jsmith-output/James Taylor/James Taylor [pvg Book]/Songs/James Taylor - Steam Roller.pdf",
        "file_size_bytes": 916155,
        "page_range": [
          44,
          48
        ]
      },
      {
        "song_title": "Blossom",
        "artist": "James Taylor",
        "output_uri": "s3://jsmith-output/James Taylor/James Taylor [pvg Book]/Songs/James Taylor - Blossom.pdf",
        "file_size_bytes": 553587,
        "page_range": [
          48,
          50
        ]
      },
      {
        "song_title": "The Blues Is Just A Bad Dream",
        "artist": "James Taylor",
        "output_uri": "s3://jsmith-output/James Taylor/James Taylor [pvg Book]/Songs/James Taylor - The Blues Is Just A Bad Dream.pdf",
        "file_size_bytes": 464476,
        "page_range": [
          50,
          52
        ]
      },
      {
        "song_title": "Rainy Day Man",
        "artist": "James Taylor",
        "output_uri": "s3://jsmith-output/James Taylor/James Taylor [pvg Book]/Songs/James Taylor - Rainy Day Man.pdf",
        "file_size_bytes": 1055244,
        "page_range": [
          52,
          56
        ]
      },
      {
        "song_title": "Knocking 'Round The Zoo",
        "artist": "James Taylor",
        "output_uri": "s3://jsmith-output/James Taylor/James Taylor [pvg Book]/Songs/James Taylor - Knocking 'round The Zoo.pdf",
        "file_size_bytes": 1225947,
        "page_range": [
          56,
          62
        ]
      },
      {
        "song_title": "Lo And Behold",
        "artist": "James Taylor",
        "output_uri": "s3://jsmith-output/James Taylor/James Taylor [pvg Book]/Songs/James Taylor - Lo And Behold.pdf",
        "file_size_bytes": 768983,
        "page_range": [
          62,
          65
        ]
      },
      {
        "song_title": "Night Owl",
        "artist": "James Taylor",
        "output_uri": "s3://jsmith-output/James Taylor/James Taylor [pvg Book]/Songs/James Taylor - Night Owl.pdf",
        "file_size_bytes": 1261193,
        "page_range": [
          65,
          70
        ]
      },
      {
        "song_title": "Suite For 20G",
        "artist": "James Taylor",
        "output_uri": "s3://jsmith-output/James Taylor/James Taylor [pvg Book]/Songs/James Taylor - Suite For 20g.pdf",
        "file_size_bytes": 1474770,
        "page_range": [
          70,
          76
        ]
      },
      {
        "song_title": "Carolina In My Mind",
        "artist": "James Taylor",
        "output_uri": "s3://jsmith-output/James Taylor/James Taylor [pvg Book]/Songs/James Taylor - Carolina In My Mind.pdf",
        "file_size_bytes": 1193922,
        "page_range": [
          76,
          81
        ]
      }
    ]
  }
}