{
  "book_id": "kenny-rogers-love-or-something-like-it-book",
  "toc": {
    "entries": [
      {
        "song_title": "Love Or Something Like It",
        "page_number": 4,
        "artist": null,
        "confidence": 0.9
      },
      {
        "song_title": "There's A Lot Of That Going Around",
        "page_number": 11,
        "artist": null,
        "confidence": 0.9
      },
      {
        "song_title": "Buried Treasures",
        "page_number": 16,
        "artist": null,
        "confidence": 0.9
      },
      {
        "song_title": "Something About Your Song",
        "page_number": 20,
        "artist": null,
        "confidence": 0.9
      },
      {
        "song_title": "Momma's Waiting",
        "page_number": 25,
        "artist": null,
        "confidence": 0.9
      },
      {
        "song_title": "We Could Have Been The Closest Of Friends",
        "page_number": 38,
        "artist": null,
        "confidence": 0.9
      },
      {
        "song_title": "I Could Be So Good For You",
        "page_number": 42,
        "artist": null,
        "confidence": 0.9
      },
      {
        "song_title": "Sail Away",
        "page_number": 48,
        "artist": null,
        "confidence": 0.9
      },
      {
        "song_title": "Even A Fool Would Let Go",
        "page_number": 54,
        "artist": null,
        "confidence": 0.9
      },
      {
        "song_title": "Highway Flyer",
        "page_number": 60,
        "artist": null,
        "confidence": 0.9
      },
      {
        "song_title": "Starting Again",
        "page_number": 64,
        "artist": null,
        "confidence": 0.9
      }
    ],
    "extraction_method": "bedrock_vision",
    "confidence": 0.9,
    "artist_overrides": {}
  },
  "output": {
    "output_files": [
      {
        "song_title": "Love Or Something Like It",
        "artist": "Kenny Rogers",
        "output_uri": "s3://jsmith-output/Kenny Rogers/Love Or Something Like It [book]/Songs/Kenny Rogers - Love Or Something Like It.pdf",
        "file_size_bytes": 113885,
        "page_range": [
          4,
          9
        ]
      },
      {
        "song_title": "There's A Lot Of That Going Around",
        "artist": "Kenny Rogers",
        "output_uri": "s3://jsmith-output/Kenny Rogers/Love Or Something Like It [book]/Songs/Kenny Rogers - There's A Lot Of That Going Around.pdf",
        "file_size_bytes": 135829,
        "page_range": [
          9,
          14
        ]
      },
      {
        "song_title": "Buried Treasures",
        "artist": "Kenny Rogers",
        "output_uri": "s3://jsmith-output/Kenny Rogers/Love Or Something Like It [book]/Songs/Kenny Rogers - Buried Treasures.pdf",
        "file_size_bytes": 93627,
        "page_range": [
          14,
          18
        ]
      },
      {
        "song_title": "Something About Your Song",
        "artist": "Kenny Rogers",
        "output_uri": "s3://jsmith-output/Kenny Rogers/Love Or Something Like It [book]/Songs/Kenny Rogers - Something About Your Song.pdf",
        "file_size_bytes": 141976,
        "page_range": [
          18,
          23
        ]
      },
      {
        "song_title": "Momma's Waiting",
        "artist": "Kenny Rogers",
        "output_uri": "s3://jsmith-output/Kenny Rogers/Love Or Something Like It [book]/Songs/Kenny Rogers - Momma's Waiting.pdf",
        "file_size_bytes": 240193,
        "page_range": [
          23,
          32
        ]
      },
      {
        "song_title": "I Could Be So Good For You",
        "artist": "Kenny Rogers",
        "output_uri": "s3://jsmith-output/Kenny Rogers/Love Or Something Like It [book]/Songs/Kenny Rogers - I Could Be So Good For You.pdf",
        "file_size_bytes": 157540,
        "page_range": [
          32,
          38
        ]
      },
      {
        "song_title": "Sail Away",
        "artist": "Kenny Rogers",
        "output_uri": "s3://jsmith-output/Kenny Rogers/Love Or Something Like It [book]/Songs/Kenny Rogers - Sail Away.pdf",
        "file_size_bytes": 143444,
        "page_range": [
          38,
          44
        ]
      },
      {
        "song_title": "Even A Fool Would Let Go",
        "artist": "Kenny Rogers",
        "output_uri": "s3://jsmith-output/Kenny Rogers/Love Or Something Like It [book]/Songs/Kenny Rogers - Even A Fool Would Let Go.pdf",
        "file_size_bytes": 131693,
        "page_range": [
          44,
          49
        ]
      },
      {
        "song_title": "Highway Flyer",
        "artist": "Kenny Rogers",
        "output_uri": "s3://jsmith-output/Kenny Rogers/Love Or Something Like It [book]/Songs/Kenny Rogers - Highway Flyer.pdf",
        "file_size_bytes": 98181,
        "page_range": [
          49,
          53
        ]
      },
      {
        "song_title": "Starting Again",
        "artist": "Kenny Rogers",
        "output_uri": "s3://jsmith-output/Kenny Rogers/Love Or Something Like It [book]/Songs/Kenny Rogers - Starting Again.pdf",
        "file_size_bytes": 88601,
        "page_range": [
          53,
          56
        ]
      }
    ]
  }
}